sonnen_charger_modbus/__init__.py
sonnen_charger_modbus/sonnencharger.py
sonnen_charger_modbus-0.1.5.dist-info/LICENSE
sonnen_charger_modbus-0.1.5.dist-info/METADATA
sonnen_charger_modbus-0.1.5.dist-info/WHEEL
sonnen_charger_modbus-0.1.5.dist-info/top_level.txt
sonnen_charger_modbus-0.1.5.dist-info/RECORD
