Metadata-Version: 2.1
Name: sonnen-charger-modbus
Version: 0.1.5
Summary: Allows to access Sonnen Charger (or any other ETREL INCH) using TCP Modbus
Home-page: https://github.com/abauske/sonnen_charger_modbus
Author: Adrian Bauske
Author-email: adrian.bauske@gmail.com
License: MIT License
License-File: LICENSE
Requires-Dist: pymodbus (~=3.1.3)
